{
  "header": {
    "cid": "blake3-512:e71e79ff6a7148d5a79c419ccc7b9218628d39f9ba1ac3d13a906cb9de24a55cfe53ac442c6708abed5f389880daccb2e5ab6b29a84b726775407b2f01272bd7",
    "content": {
      "target_language": "java",
      "template_name": "java-canonical-bodies-jackson",
      "entries": [
        {
          "concept_name": "concept:json-parse",
          "emission_template": {
            "kind": "verbatim",
            "template": "// __fragment_imports__: com.fasterxml.jackson.databind.JsonNode, com.fasterxml.jackson.databind.ObjectMapper, com.fasterxml.jackson.core.JsonProcessingException\n        try {\n            return MAPPER.readTree(${param0});\n        } catch (JsonProcessingException e) {\n            throw new RuntimeException(\"json-parse: \" + e.getMessage(), e);\n        }\n    "
          },
          "loss_record_contribution": {
            "form": "literal",
            "value": {
              "entries": []
            }
          },
          "signature_guard": {
            "min_params": 1,
            "max_params": 1
          },
          "target_library_tag": "jackson",
          "file_helpers": [
            "static final ObjectMapper MAPPER = new ObjectMapper();"
          ]
        },
        {
          "concept_name": "concept:json-serialize",
          "emission_template": {
            "kind": "verbatim",
            "template": "// __fragment_imports__: com.fasterxml.jackson.databind.JsonNode, com.fasterxml.jackson.databind.ObjectMapper, com.fasterxml.jackson.core.JsonProcessingException\n        try {\n            return MAPPER.writeValueAsString(${param0});\n        } catch (JsonProcessingException e) {\n            throw new RuntimeException(\"json-serialize: \" + e.getMessage(), e);\n        }\n    "
          },
          "loss_record_contribution": {
            "form": "literal",
            "value": {
              "entries": [
                "non-canonical-key-order"
              ]
            }
          },
          "signature_guard": {
            "min_params": 1,
            "max_params": 1
          },
          "target_library_tag": "jackson",
          "file_helpers": [
            "static final ObjectMapper MAPPER = new ObjectMapper();"
          ]
        }
      ]
    }
  }
}
