{
  "header": {
    "cid": "blake3-512:3bf9283f2db9ef9edabd2bfbc68f11dfcc99e6fbfa048e243d7adb70cd4f6191ab9d9d1256b37d442c6239e465be65127c3ad78b8a5b96207a58b4d691b88ac0",
    "content": {
      "target_language": "java",
      "template_name": "java-canonical-bodies-java-io",
      "entries": [
        {
          "concept_name": "concept:stdio-read-line",
          "emission_template": {
            "kind": "verbatim",
            "template": "// __fragment_imports__: java.io.BufferedReader, java.io.IOException, java.io.InputStreamReader, java.io.UncheckedIOException\n        try {\n            return STDIN_READER.readLine();\n        } catch (IOException e) {\n            throw new UncheckedIOException(e);\n        }\n    "
          },
          "loss_record_contribution": {
            "form": "literal",
            "value": {
              "entries": []
            }
          },
          "signature_guard": {
            "min_params": 0,
            "max_params": 0
          },
          "target_library_tag": "java-io",
          "file_helpers": [
            "static final BufferedReader STDIN_READER = new BufferedReader(new InputStreamReader(System.in));"
          ]
        },
        {
          "concept_name": "concept:stdio-write-line",
          "emission_template": {
            "kind": "verbatim",
            "template": "// __fragment_imports__: java.io.BufferedReader, java.io.IOException, java.io.InputStreamReader, java.io.UncheckedIOException\n        System.out.println(${param0});\n    "
          },
          "loss_record_contribution": {
            "form": "literal",
            "value": {
              "entries": []
            }
          },
          "signature_guard": {
            "min_params": 1,
            "max_params": 1
          },
          "target_library_tag": "java-io",
          "file_helpers": [
            "static final BufferedReader STDIN_READER = new BufferedReader(new InputStreamReader(System.in));"
          ]
        },
        {
          "concept_name": "concept:stderr-write-line",
          "emission_template": {
            "kind": "verbatim",
            "template": "// __fragment_imports__: java.io.BufferedReader, java.io.IOException, java.io.InputStreamReader, java.io.UncheckedIOException\n        System.err.println(${param0});\n    "
          },
          "loss_record_contribution": {
            "form": "literal",
            "value": {
              "entries": []
            }
          },
          "signature_guard": {
            "min_params": 1,
            "max_params": 1
          },
          "target_library_tag": "java-io",
          "file_helpers": [
            "static final BufferedReader STDIN_READER = new BufferedReader(new InputStreamReader(System.in));"
          ]
        }
      ]
    }
  }
}
