{
  "cid": "blake3-512:031ec8ccfc9be25e7eb5c8a514dc7f732a148e4140c59248601e02aee965a223460a745b8c90b04d32fbc217399f56c1066a5820a0e24003b4531f273fab4d1a",
  "memento": {
    "fn_name": "gap:php:bitand:to:concept:bitand",
    "gap_kind": "sort-mismatch",
    "kind": "TransportGapMemento",
    "reason": {
      "formal_sorts_delta": {
        "got": [
          {
            "kind": "ctor",
            "name": "Value",
            "args": []
          },
          {
            "kind": "ctor",
            "name": "Value",
            "args": []
          }
        ],
        "want": [
          {
            "kind": "ctor",
            "name": "Int",
            "args": []
          },
          {
            "kind": "ctor",
            "name": "Int",
            "args": []
          }
        ]
      }
    },
    "reason_note": "formal sort mismatch: got `[{\"kind\":\"ctor\",\"name\":\"Value\",\"args\":[]},{\"kind\":\"ctor\",\"name\":\"Value\",\"args\":[]}]` want `[{\"kind\":\"ctor\",\"name\":\"Int\",\"args\":[]},{\"kind\":\"ctor\",\"name\":\"Int\",\"args\":[]}]`",
    "resolution_options": [
      {
        "option_kind": "accept-permanent",
        "tradeoff": "formal sort mismatch: got `[{\"kind\":\"ctor\",\"name\":\"Value\",\"args\":[]},{\"kind\":\"ctor\",\"name\":\"Value\",\"args\":[]}]` want `[{\"kind\":\"ctor\",\"name\":\"Int\",\"args\":[]},{\"kind\":\"ctor\",\"name\":\"Int\",\"args\":[]}]`",
        "status": "recommended"
      }
    ],
    "schema_version": "1",
    "signature": null,
    "source_lang": "php",
    "source_op_cid": "blake3-512:caed69c1caa839a3031b5b67ca54eee891e8ec477ea507ee0e1d1bf1dfeb9be6de5c5bfe3511383b2ff6eb240897b4cb68db25daa66e99323b93af7e2daf4f4e",
    "target_concept_op": "concept:bitand",
    "target_op_cid": "blake3-512:a83de04ab992aad5eb9e1a1bb2b6706576e42d243464ad6d5aeb3a06283c6498d2325cdb3beeecae9fe1e82b684abc4c118092f6a9129281aeca5246433f4a6a"
  },
  "signature": null
}
