{
  "memento": {
    "schema_version": "1",
    "protocol": "LSP",
    "kind": "SortMemento",
    "fn_name": "rust:String",
    "formals": [],
    "formal_sorts": [],
    "pre": {
      "kind": "atomic",
      "name": "true",
      "args": []
    },
    "post": {
      "kind": "sort-description",
      "name": "String",
      "description": "Rust string values"
    },
    "effects": {
      "effects": []
    },
    "auto_minted_mementos": [],
    "return_sort": {
      "kind": "kind",
      "name": "*"
    }
  },
  "cid": "blake3-512:8a433ce8c98904119e2f62d13fc88d4c2053084998c17d085a2a045a16a5acae8f6a46bb5245e0c82dad2004239704bd51a311baf103f36784c6366fbc72f750",
  "signature": {
    "alg": "ed25519",
    "key_id": "UNSIGNED_DEV_ONLY",
    "sig_b64": "Ih3dG2wrVIBDSpSwZr/Q/yzp4TAW6mMVAOycrJrKNYrTi+t66Jhpwjeo6XHqKYkFpv02dCThGwNm/449XJvKBg=="
  }
}