{
  "memento": {
    "schema_version": "1",
    "protocol": "AMP",
    "kind": "AlgorithmMemento",
    "fn_name": "php:eq",
    "formals": [
      "lhs",
      "rhs"
    ],
    "formal_sorts": [
      {
        "kind": "ctor",
        "name": "Value",
        "args": []
      },
      {
        "kind": "ctor",
        "name": "Value",
        "args": []
      }
    ],
    "pre": {
      "kind": "atomic",
      "name": "true",
      "args": []
    },
    "post": {
      "kind": "operation-contract",
      "operator": "eq",
      "arity": [
        "Value",
        "Value"
      ],
      "result": "Value",
      "wp": "PHP == operator",
      "arity_shape": {
        "kind": "named",
        "slots": [
          {
            "name": "lhs"
          },
          {
            "name": "rhs"
          }
        ]
      }
    },
    "effects": {
      "effects": []
    },
    "auto_minted_mementos": [],
    "return_sort": {
      "kind": "ctor",
      "name": "Value",
      "args": []
    },
    "locus": "menagerie/php-language-signature/README.md#operations"
  },
  "cid": "blake3-512:25098b7c71e425c5ac9be9a31792aeb3f1aee48500ddc83c41518997aa3f1e6b3d8625167ca3d3b96f22b74868f9b735a9c676339f82d8ab586e479a0cfa7698",
  "signature": {
    "alg": "ed25519",
    "key_id": "UNSIGNED_DEV_ONLY",
    "sig_b64": "aWVcDCyuQNnfGAqTz4g+rtWyY4m2q4fySGhh1UAZHPGGZ5WFUtTWCDYAM3sv07b7nSiTGKW4ISfXrHjTCt5kAg=="
  }
}