{
  "memento": {
    "schema_version": "1",
    "protocol": "LSP",
    "kind": "EquationMemento",
    "fn_name": "rust:if-true",
    "formals": [
      "a",
      "b"
    ],
    "formal_sorts": [
      "blake3-512:75fc250ff9c62d4934b6728a1cbbd2a306f6df1c29bbcb8c7d8b77697a54ed3ac0e5bfcc4c424aed9b8aca825cb313cef5b94c023e071bb73878bde57135b106",
      "blake3-512:75fc250ff9c62d4934b6728a1cbbd2a306f6df1c29bbcb8c7d8b77697a54ed3ac0e5bfcc4c424aed9b8aca825cb313cef5b94c023e071bb73878bde57135b106"
    ],
    "pre": {
      "kind": "atomic",
      "name": "true",
      "args": []
    },
    "post": {
      "kind": "equation",
      "lhs": {
        "kind": "op",
        "name": "if",
        "args": [
          {
            "kind": "const",
            "value": true,
            "sort": {
              "kind": "ctor",
              "name": "Bool",
              "args": []
            }
          },
          {
            "kind": "var",
            "name": "a"
          },
          {
            "kind": "var",
            "name": "b"
          }
        ]
      },
      "rhs": {
        "kind": "var",
        "name": "a"
      }
    },
    "effects": {
      "effects": []
    },
    "auto_minted_mementos": [],
    "return_sort": {
      "kind": "primitive",
      "name": "Bool"
    }
  },
  "cid": "blake3-512:e478789d2eb512f73593b0d8d891474b65c0694a0533cd44e246d411e2a2efa3e1b20742393c2ae59dd69147b5fafc46368b8b25de101bc8cba351a57a8d04eb",
  "signature": {
    "alg": "ed25519",
    "key_id": "UNSIGNED_DEV_ONLY",
    "sig_b64": "rrtoEtRG+oBgtcEvPc2j+C5MVIsdr1eh4bKNl2sqM3roNmsOIoYESrchorweYtLEbiq3d0XoIIavHQLS1joJDg=="
  }
}