{"ir":[{"function":"run_server","kind":"lift-term-shape-entry","param_names":["adapter"],"param_types":["AdapterLifter"],"return_type":"void","term_shape":{"args":[{"args":[{"arity":"1","concept_name":"method:stderr_write_line","kind":"method","text":"stderr_write_line"},{"args":[{"kind":"symbol","text":"String"},{"arity":"2","concept_name":"method:format","kind":"method","text":"format"},{"kind":"const","value":"%s listening on stdio (JSON-RPC 2.0, NDJSON)"},{"args":[{"kind":"symbol","text":"adapter"},{"arity":"0","concept_name":"method:name","kind":"method","text":"name"}],"concept_name":"concept:call"}],"concept_name":"concept:call"}],"concept_name":"concept:call"},{}],"concept_name":"concept:seq"}},{"function":"handle_line","kind":"lift-term-shape-entry","param_names":["line","adapter"],"param_types":["String","AdapterLifter"],"return_type":"Object[]","term_shape":{"args":[{},{},{},{},{},{},{},{}],"concept_name":"concept:seq"}},{"function":"initialize_result","kind":"lift-term-shape-entry","param_names":["adapter"],"param_types":["AdapterLifter"],"return_type":"com.fasterxml.jackson.databind.JsonNode","term_shape":{"args":[{"args":[{},{"arity":"0","concept_name":"method:get","kind":"method","text":"get"}],"concept_name":"concept:call"}],"concept_name":"concept:return"}},{"function":"lift","kind":"lift-term-shape-entry","param_names":["params","adapter"],"param_types":["com.fasterxml.jackson.databind.JsonNode","AdapterLifter"],"return_type":"com.provekit.runtime.Result<com.fasterxml.jackson.databind.JsonNode,com.provekit.runtime.SumVariant>","term_shape":{"args":[{},{},{},{},{},{},{},{"args":[{"args":[],"concept_name":"concept:fallible-ok"}],"concept_name":"concept:return"}],"concept_name":"concept:seq"}},{"function":"build_ir_document","kind":"lift-term-shape-entry","param_names":["workspace_root","source_paths","adapter"],"param_types":["java.nio.file.Path","java.util.List<String>","AdapterLifter"],"return_type":"com.fasterxml.jackson.databind.JsonNode","term_shape":{"args":[{},{},{},{},{},{},{"args":[{"args":[{},{"arity":"0","concept_name":"method:get","kind":"method","text":"get"}],"concept_name":"concept:call"}],"concept_name":"concept:return"}],"concept_name":"concept:seq"}},{"function":"content_addressed_name","kind":"lift-term-shape-entry","param_names":["original_name","memento"],"param_types":["String","com.fasterxml.jackson.databind.JsonNode"],"return_type":"String","term_shape":{"args":[{},{},{},{},{},{"args":[{"args":[{"kind":"symbol","text":"String"},{"arity":"3","concept_name":"method:format","kind":"method","text":"format"},{"kind":"const","value":"%s#%s"},{"kind":"symbol","text":"original_name"},{"kind":"symbol","text":"content_cid"}],"concept_name":"concept:call"}],"concept_name":"concept:return"}],"concept_name":"concept:seq"}},{"function":"slot_cid","kind":"lift-term-shape-entry","param_names":["memento","key"],"param_types":["com.fasterxml.jackson.databind.JsonNode","String"],"return_type":"String","term_shape":{"args":[{},{}],"concept_name":"concept:seq"}},{"function":"blake3_512_cid","kind":"lift-term-shape-entry","param_names":["bytes"],"param_types":["byte[]"],"return_type":"String","term_shape":{"args":[{},{},{"args":[{"kind":"symbol","text":"s"},{"arity":"1","concept_name":"method:append","kind":"method","text":"append"},{"kind":"const","value":"blake3-512:"}],"concept_name":"concept:call"},{},{"args":[{"args":[{"kind":"symbol","text":"s"},{"arity":"0","concept_name":"method:toString","kind":"method","text":"toString"}],"concept_name":"concept:call"}],"concept_name":"concept:return"}],"concept_name":"concept:seq"}},{"function":"ok_response","kind":"lift-term-shape-entry","param_names":["id","result"],"param_types":["com.fasterxml.jackson.databind.JsonNode","com.fasterxml.jackson.databind.JsonNode"],"return_type":"com.fasterxml.jackson.databind.JsonNode","term_shape":{"args":[{"args":[{},{"arity":"0","concept_name":"method:get","kind":"method","text":"get"}],"concept_name":"concept:call"}],"concept_name":"concept:return"}},{"function":"error_response","kind":"lift-term-shape-entry","param_names":["id","code","message"],"param_types":["com.fasterxml.jackson.databind.JsonNode","long","String"],"return_type":"com.fasterxml.jackson.databind.JsonNode","term_shape":{"args":[{"args":[{},{"arity":"0","concept_name":"method:get","kind":"method","text":"get"}],"concept_name":"concept:call"}],"concept_name":"concept:return"}}],"kind":"ir-document","observed_loss_record":{"citation-partial-reconstruct":[{"detail":"concept=concept:fallible-ok at 105:104","dimension":"citation-partial-reconstruct","kind":"lift-gap"}],"unrecognized-expr":[{"detail":"VariableDeclarationExpr 'var __provekit_v0 = json_parse(line)' at 65:9","dimension":"unrecognized-expr","kind":"lift-gap"},{"detail":"VariableDeclarationExpr 'com.fasterxml.jackson.databind.JsonNode req' at 66:9","dimension":"unrecognized-expr","kind":"lift-gap"},{"detail":"VariableDeclarationExpr 'var id = (/*@concept concept:value-clone source-name=cloned*/ req.get(\"id\") != null ? /*@concept con...' at 72:9","dimension":"unrecognized-expr","kind":"lift-gap"},{"detail":"VariableDeclarationExpr 'var method = ((req.get(\"method\") != null ? req.get(\"method\").asText() : null) != null ? (req.get(\"me...' at 73:9","dimension":"unrecognized-expr","kind":"lift-gap"},{"detail":"VariableDeclarationExpr 'var params = (/*@concept concept:value-clone source-name=cloned*/ req.get(\"params\") != null ? /*@con...' at 74:9","dimension":"unrecognized-expr","kind":"lift-gap"},{"detail":"VariableDeclarationExpr 'var __provekit_v1 = method' at 75:9","dimension":"unrecognized-expr","kind":"lift-gap"},{"detail":"EnclosedExpr '((java.util.function.Supplier<com.fasterxml.jackson.databind.JsonNode>) () -> {     com.fasterxml.ja...' at 90:16","dimension":"unrecognized-expr","kind":"lift-gap"},{"detail":"VariableDeclarationExpr 'com.fasterxml.jackson.databind.JsonNode workspace_root = /*@concept concept:try-unwrap*/ (com.faster...' at 94:9","dimension":"unrecognized-expr","kind":"lift-gap"},{"detail":"VariableDeclarationExpr 'com.fasterxml.jackson.databind.JsonNode source_paths_raw = /*@concept concept:try-unwrap*/ (com.fast...' at 95:9","dimension":"unrecognized-expr","kind":"lift-gap"},{"detail":"VariableDeclarationExpr 'java.util.List source_paths = java.util.stream.StreamSupport.stream(source_paths_raw.spliterator(), ...' at 96:9","dimension":"unrecognized-expr","kind":"lift-gap"},{"detail":"VariableDeclarationExpr 'var options = (/*@concept concept:value-clone source-name=cloned*/ params.get(\"options\") != null ? /...' at 97:9","dimension":"unrecognized-expr","kind":"lift-gap"},{"detail":"VariableDeclarationExpr 'var emit = ((options.get(\"emit\") != null ? ((java.util.function.Function) ((java.util.function.Funct...' at 98:9","dimension":"unrecognized-expr","kind":"lift-gap"},{"detail":"VariableDeclarationExpr 'java.nio.file.Path root = java.nio.file.Path.of(workspace_root.toString())' at 104:9","dimension":"unrecognized-expr","kind":"lift-gap"},{"detail":"VariableDeclarationExpr 'var __provekit_struct = adapter.lift(workspace_root, source_paths)' at 109:9","dimension":"unrecognized-expr","kind":"lift-gap"},{"detail":"VariableDeclarationExpr 'var mementos = __provekit_struct.get(\"mementos\")' at 110:9","dimension":"unrecognized-expr","kind":"lift-gap"},{"detail":"VariableDeclarationExpr 'var diagnostics = __provekit_struct.get(\"diagnostics\")' at 111:9","dimension":"unrecognized-expr","kind":"lift-gap"},{"detail":"VariableDeclarationExpr 'java.util.ArrayList ir_entries = new java.util.ArrayList<>()' at 112:9","dimension":"unrecognized-expr","kind":"lift-gap"},{"detail":"VariableDeclarationExpr 'java.util.TreeSet seen_names = new java.util.TreeSet<>()' at 113:9","dimension":"unrecognized-expr","kind":"lift-gap"},{"detail":"EnclosedExpr '((java.util.function.Supplier<com.fasterxml.jackson.databind.JsonNode>) () -> {     com.fasterxml.ja...' at 130:16","dimension":"unrecognized-expr","kind":"lift-gap"},{"detail":"VariableDeclarationExpr 'String inv_cid = slot_cid(memento, \"inv\")' at 134:9","dimension":"unrecognized-expr","kind":"lift-gap"},{"detail":"VariableDeclarationExpr 'String pre_cid = slot_cid(memento, \"pre\")' at 135:9","dimension":"unrecognized-expr","kind":"lift-gap"},{"detail":"VariableDeclarationExpr 'String post_cid = slot_cid(memento, \"post\")' at 136:9","dimension":"unrecognized-expr","kind":"lift-gap"},{"detail":"VariableDeclarationExpr 'String composed = String.format(\"%s|%s|%s\", inv_cid, pre_cid, post_cid)' at 137:9","dimension":"unrecognized-expr","kind":"lift-gap"},{"detail":"VariableDeclarationExpr 'String content_cid = blake3_512_cid(composed.getBytes(java.nio.charset.StandardCharsets.UTF_8))' at 138:9","dimension":"unrecognized-expr","kind":"lift-gap"},{"detail":"VariableDeclarationExpr 'var __provekit_v0 = memento.get(key)' at 143:9","dimension":"unrecognized-expr","kind":"lift-gap"},{"detail":"VariableDeclarationExpr 'var raw = blake3_512_of(bytes)' at 152:9","dimension":"unrecognized-expr","kind":"lift-gap"},{"detail":"VariableDeclarationExpr 'StringBuilder s = new StringBuilder((\"blake3-512:\".length()) + (128))' at 153:9","dimension":"unrecognized-expr","kind":"lift-gap"},{"detail":"EnclosedExpr '((java.util.function.Supplier<com.fasterxml.jackson.databind.JsonNode>) () -> {     com.fasterxml.ja...' at 163:16","dimension":"unrecognized-expr","kind":"lift-gap"},{"detail":"EnclosedExpr '((java.util.function.Supplier<com.fasterxml.jackson.databind.JsonNode>) () -> {     com.fasterxml.ja...' at 167:16","dimension":"unrecognized-expr","kind":"lift-gap"}],"unrecognized-stmt":[{"detail":"WhileStmt 'while (true) {     var line = stdin_read_line();     if ((line) == (null)) {         break;     } el...' at 39:9","dimension":"unrecognized-stmt","kind":"lift-gap"},{"detail":"IfStmt 'if ((__provekit_v0 instanceof com.provekit.runtime.Result.Ok)) {     req = __provekit_v0.unwrap(); }...' at 67:9","dimension":"unrecognized-stmt","kind":"lift-gap"},{"detail":"IfStmt 'if ((__provekit_v1 != null && __provekit_v1.equals(\"initialize\"))) {     return new Object[] { ok_re...' at 76:9","dimension":"unrecognized-stmt","kind":"lift-gap"},{"detail":"IfStmt 'if (!java.util.Objects.equals(emit, \"ir-document\")) {     return /*@concept concept:fallible-err pay...' at 99:9","dimension":"unrecognized-stmt","kind":"lift-gap"},{"detail":"ForEachStmt 'for (var memento : mementos) {     var original_name = ((memento.get(\"name\") != null ? ((java.util.f...' at 114:9","dimension":"unrecognized-stmt","kind":"lift-gap"},{"detail":"IfStmt 'if ((__provekit_v0 != null)) {     return blake3_512_cid(encode_jcs(__provekit_v0).getBytes(java.nio...' at 144:9","dimension":"unrecognized-stmt","kind":"lift-gap"},{"detail":"ForEachStmt 'for (var b : raw) {     s.append((char) (HEX[(int) ((b) >> (4))]));     s.append((char) (HEX[(int) (...' at 155:9","dimension":"unrecognized-stmt","kind":"lift-gap"}]},"sourceLanguage":"java","sourcePath":"/tmp/cp-compile/CrossPlatform.java"}