{
  "key": "src/signals/CommentSignalGenerator.ts/extractParameters[88]",
  "file": "/Users/tsavo/Projects/neurallog/src/signals/CommentSignalGenerator.ts",
  "function": "extractParameters",
  "line": 88,
  "signal_hash": "d6f8ffa33aa4bec7249c19d7f3cf37504b686a6537dd3db2d175e451c4d77d32",
  "proven": [],
  "violations": [
    {
      "principle": "empty-collection-loop",
      "principle_hash": "",
      "claim": "VIOLATION: Empty Collection Loop at extractParameters",
      "smt2": "; PRINCIPLE: empty-collection-loop\n; LINE: 88\n; VIOLATION: Empty Collection Loop at extractParameters\n(declare-const collection_size Int)\n(declare-const loop_body_executed Int)\n(assert (= collection_size 0))\n(assert (= loop_body_executed 0))\n(check-sat)",
      "witness": "(\n  (define-fun loop_body_executed () Int\n    0)\n  (define-fun collection_size () Int\n    0)\n)",
      "complexity": 0,
      "confidence": "low"
    }
  ],
  "depends_on": [],
  "clause_history": [
    {
      "clause": "; PRINCIPLE: empty-collection-loop\n; LINE: 88\n; VIOLATION: Empty Collection Loop at extractParameters\n(declare-const collection_size Int)\n(declare-const loop_body_executed Int)\n(assert (= collection_size 0))\n(assert (= loop_body_executed 0))\n(check-sat)",
      "status": "active",
      "weaken_step": 0,
      "witness_count_at_last_weaken": 0,
      "current_witness_count": 0
    }
  ]
}