{
  "effects": {
    "effects": []
  },
  "fn_name": "concept:source-unit",
  "formal_sorts": [
    {
      "args": [],
      "kind": "ctor",
      "name": "String"
    },
    {
      "args": [],
      "kind": "ctor",
      "name": "Stmt"
    }
  ],
  "formals": [
    "bytes",
    "operational_term"
  ],
  "kind": "algorithm",
  "post": {
    "arity": [
      "String",
      "Stmt"
    ],
    "arity_shape": {
      "kind": "named",
      "slots": [
        {
          "evaluation": "unevaluated",
          "name": "bytes",
          "slot_sort": "literal"
        },
        {
          "name": "operational_term"
        }
      ]
    },
    "kind": "operation-contract",
    "operator": "source-unit",
    "result": "Stmt",
    "wp": "lossless source wrapper; the source bytes are recoverable and the operational projection is operational_term",
    "wp_rule": {
      "args": [
        {
          "kind": "var",
          "name": "Q"
        }
      ],
      "fn": "wp_operational_term",
      "kind": "apply"
    }
  },
  "pre": {
    "args": [],
    "kind": "atomic",
    "name": "true"
  },
  "return_sort": {
    "args": [],
    "kind": "ctor",
    "name": "Stmt"
  }
}
