{
  "kind": "algorithm",
  "fn_name": "rust:effect:drop_glue",
  "formals": [
    "addr"
  ],
  "formal_sorts": [
    {
      "kind": "ctor",
      "name": "Addr",
      "args": []
    }
  ],
  "return_sort": {
    "kind": "ctor",
    "name": "Unit",
    "args": []
  },
  "pre": {
    "kind": "atomic",
    "name": "true",
    "args": []
  },
  "post": {
    "kind": "operation-contract",
    "operator": "drop_glue",
    "arity": [
      "Addr"
    ],
    "result": "Unit",
    "wp": "run drop glue for address"
  },
  "effects": {
    "effects": [
      {
        "kind": "effect-signature",
        "name": "Drop"
      }
    ]
  },
  "locus": "menagerie/rust-language-signature/README.md#operations"
}
