{
  "kind": "algorithm",
  "fn_name": "rust:range",
  "formals": [
    "start",
    "end"
  ],
  "formal_sorts": [
    {
      "kind": "ctor",
      "name": "Expr",
      "args": []
    },
    {
      "kind": "ctor",
      "name": "Expr",
      "args": []
    }
  ],
  "return_sort": {
    "kind": "ctor",
    "name": "Expr",
    "args": []
  },
  "pre": {
    "kind": "atomic",
    "name": "true",
    "args": []
  },
  "post": {
    "kind": "operation-contract",
    "operator": "range",
    "arity": [
      "Expr",
      "Expr"
    ],
    "result": "Expr",
    "wp": "half open range expression"
  },
  "effects": {
    "effects": []
  },
  "locus": "menagerie/rust-language-signature/README.md#operations"
}
