{
  "memento": {
    "schema_version": "1",
    "protocol": "LSP",
    "kind": "SortMemento",
    "fn_name": "java:Ref",
    "formals": [],
    "formal_sorts": [],
    "pre": {
      "kind": "atomic",
      "name": "true",
      "args": []
    },
    "post": {
      "kind": "sort-description",
      "name": "Ref",
      "description": "Java object or array reference value."
    },
    "effects": {
      "effects": []
    },
    "auto_minted_mementos": [],
    "return_sort": {
      "kind": "kind",
      "name": "*"
    }
  },
  "cid": "blake3-512:ce36d6b03f5bf92d45f2859c37fb3ef5caafe17cbc7a85659ecac8c6622b307e42f068a5782a92a6de1b4161e8876462677ea332067f5313e62277c84ec327d2",
  "signature": {
    "alg": "ed25519",
    "key_id": "UNSIGNED_DEV_ONLY",
    "sig_b64": "59my5g5LNLWqDPn6wl3DqygxbD/LjJmqxoj3a5PBzSNj4WBbhehPTdaDfAAB/e+ClPFUR/36FxVKUKohS80WAA=="
  }
}